fdc/__init__.py
fdc/classify.py
fdc/density_estimation.py
fdc/fdc.py
fdc/graph.py
fdc/hierarchy.py
fdc/mycolors.py
fdc/plotting.py
fdc/robustness.py
fdc/special_datasets.py
fdc/tree.py
fdc/tree_old.py
fdc/utils.py
fdc/widget.py
fdc-1.15.dist-info/METADATA
fdc-1.15.dist-info/RECORD
fdc-1.15.dist-info/WHEEL
fdc-1.15.dist-info/top_level.txt
