Metadata-Version: 2.1
Name: fdc
Version: 1.15
Summary: Fast Density Clustering in low-dimension
Home-page: https://alexandreday.github.io/
Author: Alexandre Day
Author-email: alexandre.day1@gmail.com
License: MIT
Platform: UNKNOWN
Classifier: Programming Language :: Python :: 3
Classifier: License :: OSI Approved :: MIT License
Classifier: Operating System :: OS Independent
Requires-Dist: scikit-learn (>=0.19)
